llmwrite/__init__.py
llmwrite/accepted_language.py
llmwrite/core.py
llmwrite/lang_conf.py
llmwrite/locales/messages.en.yaml
llmwrite/locales/messages.ja.yaml
llmwrite/main.py
llmwrite/prompts.py
llmwrite/questionary_ui.py
llmwrite-0.1.5.dist-info/LICENSE
llmwrite-0.1.5.dist-info/METADATA
llmwrite-0.1.5.dist-info/WHEEL
llmwrite-0.1.5.dist-info/entry_points.txt
llmwrite-0.1.5.dist-info/RECORD
