Metadata-Version: 2.1
Name: llmwrite
Version: 0.1.5
Summary: CLI for Automated article writing (Powered by GPT-3)
Home-page: https://github.com/otakumesi/llm-write
License: MIT
Keywords: gpt,openai,cli,article,writing
Author: otakumesi
Author-email: bakednt@gmail.com
Requires-Python: >=3.8,<4.0
Classifier: License :: OSI Approved :: MIT License
Classifier: Programming Language :: Python :: 3
Classifier: Programming Language :: Python :: 3.8
Classifier: Programming Language :: Python :: 3.9
Classifier: Programming Language :: Python :: 3.10
Classifier: Programming Language :: Python :: 3.11
Requires-Dist: click
Requires-Dist: iso639-lang
Requires-Dist: openai
Requires-Dist: python-i18n[yaml]
Requires-Dist: questionary (>=1.10.0,<2.0.0)
Requires-Dist: yaspin (>=2.3.0,<3.0.0)
Project-URL: Repository, https://github.com/otakumesi/llm-write
